textfindreplace/__init__.py
textfindreplace/exceptions.py
textfindreplace/find_engine.py
textfindreplace/replace_engine.py
textfindreplace-0.1.0.dist-info/METADATA
textfindreplace-0.1.0.dist-info/WHEEL
textfindreplace-0.1.0.dist-info/top_level.txt
textfindreplace-0.1.0.dist-info/RECORD
