Metadata-Version: 2.4
Name: textfindreplace
Version: 0.1.0
Summary: Engine reutilizável de find/replace em texto puro
Author: Dado Beltrão
License: MIT
Project-URL: Source, https://example.com
Requires-Python: >=3.8
